parguments
