Metadata-Version: 1.0
Name: parguments
Version: 0.3.2
Summary: Parguments: A simple cli args parser for Python
Home-page: https://github.com/whtsky/parguments
Author: whtsky
Author-email: whtsky@me.com
License: MIT
Platform: UNKNOWN
Classifier: Development Status :: 3 - Alpha
Classifier: Topic :: Utilities
Classifier: Operating System :: MacOS
Classifier: Operating System :: POSIX
Classifier: Operating System :: POSIX :: Linux
Classifier: Programming Language :: Python :: 2.6
Classifier: Programming Language :: Python :: 2.7
Classifier: Programming Language :: Python :: 3.2
Classifier: Programming Language :: Python :: 3.3
Classifier: License :: OSI Approved :: MIT License
